netlink/sap/monitor/__init__.py
netlink/sap/monitor/core/__init__.py
netlink/sap/monitor/core/age_bracket.py
netlink/sap/monitor/lock/__init__.py
netlink/sap/monitor/lock/lock_entry.py
netlink/sap/monitor/rfc/__init__.py
netlink/sap/monitor/rfc/trfc_calls.py
netlink/sap/monitor/updater/__init__.py
netlink/sap/monitor/updater/updater_queue.py
netlink_sap_monitor-0.0.4.dist-info/WHEEL
netlink_sap_monitor-0.0.4.dist-info/METADATA
netlink_sap_monitor-0.0.4.dist-info/RECORD
